{
  "id": "paraflow/advanced/tables",
  "title": "Tables",
  "description": "Paraflow programs can define and manipulate application tables that are stored in a database, as well as small in-memory tables represented by a local variable. The language provides statements for creating, deleting, updating, and querying tables.",
  "source": "@site/docs/paraflow/advanced/tables.md",
  "sourceDirName": "paraflow/advanced",
  "slug": "/paraflow/advanced/tables",
  "permalink": "/docs/paraflow/advanced/tables",
  "draft": false,
  "unlisted": false,
  "editUrl": "https://github.com/otonoma/paranet/edit/main/docs/docs/paraflow/advanced/tables.md",
  "tags": [],
  "version": "current",
  "sidebarPosition": 4,
  "frontMatter": {
    "id": "tables",
    "title": "Tables",
    "sidebar_position": 4
  },
  "sidebar": "tutorialSidebar",
  "previous": {
    "title": "Skills",
    "permalink": "/docs/paraflow/advanced/skills"
  },
  "next": {
    "title": "Control Flow",
    "permalink": "/docs/paraflow/advanced/control_flow"
  }
}